mudclientprotocol/__init__.py
mudclientprotocol-0.2.0.dist-info/DESCRIPTION.rst
mudclientprotocol-0.2.0.dist-info/METADATA
mudclientprotocol-0.2.0.dist-info/RECORD
mudclientprotocol-0.2.0.dist-info/WHEEL
mudclientprotocol-0.2.0.dist-info/metadata.json
mudclientprotocol-0.2.0.dist-info/top_level.txt
